beepy_bluetooth_manager/main.py
beepy_bluetooth_manager-0.1.2.dist-info/LICENSE
beepy_bluetooth_manager-0.1.2.dist-info/METADATA
beepy_bluetooth_manager-0.1.2.dist-info/WHEEL
beepy_bluetooth_manager-0.1.2.dist-info/entry_points.txt
beepy_bluetooth_manager-0.1.2.dist-info/RECORD
